pyxit/__init__.py
pyxit/data.py
pyxit/estimator.py
pyxit/util.py
pyxit-1.1.3.dist-info/DESCRIPTION.rst
pyxit-1.1.3.dist-info/METADATA
pyxit-1.1.3.dist-info/RECORD
pyxit-1.1.3.dist-info/WHEEL
pyxit-1.1.3.dist-info/metadata.json
pyxit-1.1.3.dist-info/top_level.txt
